{
 "actions": [],
 "allow_rename": 1,
 "autoname": "format:TOUR-{#####}",
 "creation": "2026-06-17 16:12:56.943588",
 "default_view": "List",
 "doctype": "DocType",
 "engine": "InnoDB",
 "field_order": [
  "employee",
  "employee_name",
  "purpose_of_travel",
  "no_of_days",
  "column_break_egn7",
  "travel_request_date",
  "from_date",
  "to_date",
  "comp_off_created",
  "amended_from"
 ],
 "fields": [
  {
   "fieldname": "amended_from",
   "fieldtype": "Link",
   "label": "Amended From",
   "no_copy": 1,
   "options": "Tour Request",
   "print_hide": 1,
   "read_only": 1,
   "search_index": 1
  },
  {
   "fieldname": "employee",
   "fieldtype": "Link",
   "in_list_view": 1,
   "in_standard_filter": 1,
   "label": "Employee",
   "options": "Employee",
   "reqd": 1
  },
  {
   "default": "Today",
   "fieldname": "travel_request_date",
   "fieldtype": "Date",
   "in_list_view": 1,
   "in_standard_filter": 1,
   "label": "Travel Request Date",
   "reqd": 1
  },
  {
   "fieldname": "from_date",
   "fieldtype": "Date",
   "in_list_view": 1,
   "in_standard_filter": 1,
   "label": "From Date",
   "reqd": 1
  },
  {
   "fieldname": "to_date",
   "fieldtype": "Date",
   "in_list_view": 1,
   "in_standard_filter": 1,
   "label": "To Date",
   "reqd": 1
  },
  {
   "fieldname": "purpose_of_travel",
   "fieldtype": "Data",
   "in_list_view": 1,
   "label": "Purpose of Travel",
   "reqd": 1
  },
  {
   "fetch_from": "employee.employee_name",
   "fieldname": "employee_name",
   "fieldtype": "Data",
   "in_list_view": 1,
   "in_standard_filter": 1,
   "label": "Employee Name",
   "read_only": 1
  },
  {
   "default": "Today",
   "fieldname": "column_break_egn7",
   "fieldtype": "Column Break"
  },
  {
   "fieldname": "no_of_days",
   "fieldtype": "Data",
   "in_list_view": 1,
   "label": "No of Days",
   "read_only": 1
  },
  {
   "default": "0",
   "fieldname": "comp_off_created",
   "fieldtype": "Check",
   "hidden": 1,
   "label": "Comp off Created"
  }
 ],
 "grid_page_length": 50,
 "index_web_pages_for_search": 1,
 "is_submittable": 1,
 "links": [],
 "modified": "2026-06-23 09:53:26.408320",
 "modified_by": "Administrator",
 "module": "JKMPCL HR",
 "name": "Tour Request",
 "naming_rule": "Expression (old style)",
 "owner": "Administrator",
 "permissions": [],
 "row_format": "Dynamic",
 "rows_threshold_for_grid_search": 20,
 "sort_field": "creation",
 "sort_order": "DESC",
 "states": [],
 "track_changes": 1,
 "track_seen": 1,
 "track_views": 1
}
